CHANGES.txt
README.txt
bootstrap.py
setup.py
src/z3c/__init__.py
src/z3c.language.session.egg-info/PKG-INFO
src/z3c.language.session.egg-info/SOURCES.txt
src/z3c.language.session.egg-info/dependency_links.txt
src/z3c.language.session.egg-info/namespace_packages.txt
src/z3c.language.session.egg-info/not-zip-safe
src/z3c.language.session.egg-info/requires.txt
src/z3c.language.session.egg-info/top_level.txt
src/z3c/language/__init__.py
src/z3c/language/session/README.txt
src/z3c/language/session/SETUP.cfg
src/z3c/language/session/__init__.py
src/z3c/language/session/app.py
src/z3c/language/session/configure.zcml
src/z3c/language/session/interfaces.py
src/z3c/language/session/tests.py
src/z3c/language/session/z3c.language.session-configure.zcml
src/z3c/language/session/browser/__init__.py
src/z3c/language/session/browser/configure.zcml
src/z3c/language/session/browser/views.py
src/z3c/language/session/generations/__init__.py
src/z3c/language/session/generations/configure.zcml